{
  "name": "vite_react_shadcn_ts",
  "private": true,
  "version": "0.0.0",
  "type": "module",
  "scripts": {
    "dev": "vite --config vite.config.ts",
    "dev:debug": "vite --config vite.config.ts --debug",
    "dev:strict": "tsc --noEmit --project tsconfig.dev.json && vite --config vite.config.ts",
    "dev:full": "concurrently \"npm run mock-persona\" \"npm run dev\"",
    "dev:analyze": "vite build --mode development && npx vite-bundle-analyzer dist/stats.html",
    "mock-persona": "node scripts/mock-persona-server.js",
    "build": "tsc && vite build",
    "build:dev": "tsc && vite build --mode development",
    "type-check": "tsc --noEmit --project tsconfig.dev.json",
    "type-check:watch": "tsc --noEmit --watch --project tsconfig.dev.json",
    "lint": "eslint . --ext ts,tsx --report-unused-disable-directives --max-warnings 0",
    "lint:fix": "eslint . --ext ts,tsx --fix",
    "preview": "vite preview",
    "test": "jest --runInBand",
    "test:ci": "jest --ci --runInBand --coverage --reporters=default --reporters=jest-junit",
    "test:ci:fast": "jest --ci --maxWorkers=2 --coverage --bail=1",
    "test:qa-unit": "jest --testPathPattern=quality-assurance",
    "test:qa-api": "jest --testPathPattern=qa-server",
    "jest:version": "node -e \"console.log('jest=',require('jest/package.json').version);try{console.log('jsdomEnv=',require('jest-environment-jsdom/package.json').version)}catch(e){console.log('jsdomEnv=not installed')}\"",
    "test:green-core": "./scripts/run-green-core-tests-minimal.sh",
    "test:jest": "jest --maxWorkers=50%",
    "test:deno": "deno test test/unit",
    "test:smoke": "playwright test",
    "test:e2e": "playwright test -c playwright.config.ts",
    "test:e2e:headed": "playwright test -c playwright.config.ts --headed",
    "test:visual": "playwright test -c playwright.visual.config.ts",
    "test:performance": "lhci autorun",
    "test:cross-browser": "playwright test -c playwright.cross-browser.config.ts",
    "test:qa": "npm run test:qa-unit && npm run test:qa-api && npm run test:e2e && npm run test:visual && npm run test:cross-browser && npm run test:performance",
    "test:all": "npm run test && npm run test:qa",
    "test:lambda": "cd infra/lambdas && npm test",
    "test:security": "npm run test:lambda -- --testNamePattern='Red Team'",
    "test:watch": "jest --runInBand --watchAll=false",
    "test:coverage": "jest --coverage --watchAll=false",
    "test:coverage:ci": "jest --ci --coverage --watchAll=false --reporters=default --reporters=jest-junit",
    "test:coverage:threshold": "jest --coverage --watchAll=false --coverageThreshold='{\"global\":{\"branches\":70,\"functions\":70,\"lines\":70,\"statements\":70}}'",
    "test:ci:enhanced": "node scripts/jest/ci-test-runner.cjs --coverage --fail-fast",
    "test:coverage:validate": "node scripts/jest/coverage-validator.cjs",
    "test:optimized": "node scripts/jest/run-optimized-tests.cjs --optimize",
    "test:optimized:coverage": "node scripts/jest/run-optimized-tests.cjs --coverage --optimize --validate-coverage",
    "test:optimized:fast": "node scripts/jest/run-optimized-tests.cjs --fail-fast --optimize",
    "test:suite:core": "node scripts/jest/run-optimized-tests.cjs --suite=core --optimize",
    "test:suite:performance": "node scripts/jest/run-optimized-tests.cjs --suite=performance --coverage --optimize",
    "test:ms:unit": "jest --config jest.microservices.config.cjs --selectProjects unit",
    "test:ms:ui": "jest --config jest.microservices.config.cjs --selectProjects ui",
    "test:ms:cdk": "jest --config jest.microservices.config.cjs --selectProjects cdk",
    "test:ms:all": "npm run test:ms:cdk && npm run test:ms:unit && npm run test:ms:ui",
    "qa:full": "npx tsx scripts/run-qa-analysis.ts",
    "qa:quick": "npx tsx scripts/run-qa-analysis.ts --quick",
    "qa:code-review": "npx tsx scripts/run-qa-analysis.ts --code-review-only",
    "qa:security": "npx tsx scripts/run-qa-analysis.ts --security-only",
    "qa:accessibility": "npx tsx scripts/run-qa-analysis.ts --accessibility-only",
    "qa:quality-gates": "npx tsx scripts/run-qa-analysis.ts --quality-gates-only",
    "qa:summary": "npx tsx scripts/generate-qa-summary.ts",
    "security:scan": "npx tsx scripts/run-security-scan.ts",
    "security:scan:quick": "npx tsx scripts/run-security-scan.ts --scan-type quick",
    "security:scan:standard": "npx tsx scripts/run-security-scan.ts --scan-type standard",
    "security:scan:comprehensive": "npx tsx scripts/run-security-scan.ts --scan-type comprehensive --penetration-testing",
    "security:compliance": "npx tsx scripts/run-security-scan.ts --compliance-only",
    "test:load-10x": "npx tsx scripts/run-10x-load-test.ts",
    "test:load-10x:scalability": "npx tsx scripts/run-10x-load-test.ts --type scalability",
    "test:load-10x:endurance": "npx tsx scripts/run-10x-load-test.ts --type endurance",
    "test:load-10x:breaking-point": "npx tsx scripts/run-10x-load-test.ts --type breaking-point",
    "test:load-10x:production": "npx tsx scripts/run-10x-load-test.ts --env production --target https://api.matbakh.app",
    "qa:server": "npx tsx scripts/qa-server.ts",
    "qa:server:dev": "npx tsx --watch scripts/qa-server.ts",
    "check-legal": "node scripts/check-legal-consistency.js",
    "gen:component": "npx tsx scripts/generators/component.ts",
    "gen:api": "npx tsx scripts/generators/api.ts",
    "gen:tests": "npx tsx scripts/generators/tests.ts",
    "gen:docs": "npx tsx scripts/generators/docs.ts",
    "gen:validate": "npm run lint && npm run type-check && npm test && npx tsx scripts/system-state-validator.ts",
    "check:nav": "node scripts/check-navigation-consistency.js",
    "archive:consolidate": "npx tsx scripts/consolidate-archival-systems.ts",
    "archive:safe": "npx tsx scripts/run-safe-archival.ts",
    "archive:verify": "bash scripts/verify-archive.sh",
    "archive:restore": "npx tsx scripts/restore-onhold-component.ts",
    "deploy": "tsx scripts/deploy-one-click.ts",
    "deploy:dev": "tsx scripts/deploy-one-click.ts --env development",
    "deploy:staging": "tsx scripts/deploy-one-click.ts --env staging",
    "deploy:prod": "tsx scripts/deploy-one-click.ts --env production",
    "deploy:package": "tsx scripts/deploy/package-artifact.ts",
    "deploy:sync": "tsx scripts/deploy/sync-to-slot.ts",
    "deploy:switch": "tsx scripts/deploy/switch-origin.ts",
    "deploy:smoke": "tsx scripts/deploy/smoke-suite.ts",
    "deploy:rollback": "tsx scripts/deploy/deployment-rollback.ts",
    "rollback": "tsx scripts/deploy/deployment-rollback.ts",
    "deploy:validate": "npm run deploy:smoke && npm run qa:quick",
    "deploy:verify-staging": "DEPLOY_SMOKE_BASE=https://matbakh.app/$DEPLOY_SLOT npm run deploy:validate",
    "deploy:verify-prod": "DEPLOY_SMOKE_BASE=https://matbakh.app/$DEPLOY_SLOT npm run deploy:validate",
    "check:health": "tsx scripts/check-deployment-health.ts",
    "archive:rollback": "bash src/archive/consolidated-legacy-archive-2025-09-18/rollback.sh",
    "kiro:purity": "npx tsx scripts/run-kiro-purity-working.ts",
    "kiro:purity:strict": "npx tsx scripts/run-kiro-purity-working.ts --timeout=25000 --max-files=4000 --concurrency=24",
    "kiro:purity:ci": "npx tsx scripts/run-kiro-purity-working.ts --timeout=25000 --max-files=4000 --concurrency=24",
    "test:mr:iac": "jest --testPathPattern=infra/cdk/__tests__",
    "test:mr:unit": "jest --testPathPattern=src/lib/multi-region/__tests__",
    "test:mr:dr": "jest --testPathPattern=scripts/__tests__/dr-",
    "test:mr:e2e": "playwright test test/e2e/multi-region-failover.spec.ts",
    "test:mr:failover": "tsx scripts/test-multi-region-failover.ts",
    "verify:task11": "npm run test:mr:iac && npm run test:mr:unit && npm run test:mr:dr",
    "verify:task11:full": "npm run test:mr:failover",
    "hooks:watch": "npx tsx scripts/kiro-hook-watcher.ts",
    "hooks:trigger": "npx tsx scripts/fix-kiro-hook-system.ts",
    "hooks:check": "npx tsx scripts/check-and-trigger-hooks.ts",
    "hooks:monitor": "npx tsx scripts/start-hook-monitoring.ts",
    "hooks:dispatch": "npx tsx scripts/dispatch-all-hooks.ts",
    "hooks:task-complete": "npx tsx scripts/dispatch-all-hooks.ts taskCompleted",
    "prepare": "husky"
  },
  "dependencies": {
    "@aws-amplify/ui-react": "^6.12.0",
    "@aws-sdk/client-cloudformation": "^3.902.0",
    "@aws-sdk/client-cognito-identity-provider": "^3.490.0",
    "@aws-sdk/client-dynamodb": "^3.887.0",
    "@aws-sdk/client-evidently": "^3.901.0",
    "@aws-sdk/client-rds-data": "^3.490.0",
    "@hookform/resolvers": "^3.3.4",
    "@radix-ui/react-accordion": "^1.2.12",
    "@radix-ui/react-alert-dialog": "^1.1.15",
    "@radix-ui/react-aspect-ratio": "^1.1.7",
    "@radix-ui/react-avatar": "^1.1.10",
    "@radix-ui/react-checkbox": "^1.3.3",
    "@radix-ui/react-collapsible": "^1.1.12",
    "@radix-ui/react-context-menu": "^2.2.16",
    "@radix-ui/react-dialog": "^1.0.5",
    "@radix-ui/react-dropdown-menu": "^2.1.16",
    "@radix-ui/react-hover-card": "^1.1.15",
    "@radix-ui/react-label": "^2.0.2",
    "@radix-ui/react-menubar": "^1.1.16",
    "@radix-ui/react-navigation-menu": "^1.2.14",
    "@radix-ui/react-popover": "^1.1.15",
    "@radix-ui/react-progress": "^1.1.7",
    "@radix-ui/react-radio-group": "^1.3.8",
    "@radix-ui/react-scroll-area": "^1.2.10",
    "@radix-ui/react-select": "^2.0.0",
    "@radix-ui/react-separator": "^1.1.7",
    "@radix-ui/react-slot": "^1.0.2",
    "@radix-ui/react-switch": "^1.2.6",
    "@radix-ui/react-tabs": "^1.1.13",
    "@radix-ui/react-toast": "^1.1.5",
    "@radix-ui/react-toggle": "^1.1.10",
    "@radix-ui/react-toggle-group": "^1.1.11",
    "@radix-ui/react-tooltip": "^1.2.8",
    "@tanstack/react-query": "^5.87.0",
    "@types/uuid": "^10.0.0",
    "@types/ws": "^8.18.1",
    "@vercel/speed-insights": "^1.0.10",
    "aws-amplify": "^6.15.6",
    "axios": "^1.12.2",
    "body-parser": "^2.2.0",
    "class-variance-authority": "^0.7.0",
    "clsx": "^2.1.0",
    "cmdk": "^1.1.1",
    "date-fns": "^3.6.0",
    "embla-carousel-react": "^8.6.0",
    "fastify": "^5.6.1",
    "i18next": "^23.10.1",
    "i18next-browser-languagedetector": "^7.2.2",
    "i18next-http-backend": "^3.0.2",
    "input-otp": "^1.4.2",
    "ioredis": "^5.3.2",
    "lucide-react": "^0.363.0",
    "next-themes": "^0.3.0",
    "pg": "^8.11.3",
    "react": "^18.2.0",
    "react-day-picker": "^9.11.0",
    "react-dnd": "^16.0.1",
    "react-dom": "^18.2.0",
    "react-helmet-async": "^2.0.4",
    "react-hook-form": "^7.51.1",
    "react-i18next": "^14.1.0",
    "react-resizable-panels": "^3.0.6",
    "react-router-dom": "^6.22.3",
    "recharts": "^2.12.2",
    "sonner": "^1.4.41",
    "tailwind-merge": "^2.2.2",
    "tailwindcss-animate": "^1.0.7",
    "uuid": "^13.0.0",
    "vaul": "^1.1.2",
    "web-vitals": "^5.1.0",
    "ws": "^8.18.3",
    "zod": "^3.22.4"
  },
  "devDependencies": {
    "@aws-sdk/client-application-auto-scaling": "^3.887.0",
    "@aws-sdk/client-bedrock-runtime": "^3.896.0",
    "@aws-sdk/client-budgets": "^3.896.0",
    "@aws-sdk/client-cloudfront": "^3.887.0",
    "@aws-sdk/client-cloudwatch": "^3.887.0",
    "@aws-sdk/client-cloudwatch-logs": "^3.888.0",
    "@aws-sdk/client-elasticache": "^3.887.0",
    "@aws-sdk/client-kms": "^3.896.0",
    "@aws-sdk/client-lambda": "^3.887.0",
    "@aws-sdk/client-rds": "^3.887.0",
    "@aws-sdk/client-route-53": "^3.896.0",
    "@aws-sdk/client-s3": "^3.888.0",
    "@aws-sdk/client-sagemaker": "^3.899.0",
    "@aws-sdk/client-secrets-manager": "^3.896.0",
    "@aws-sdk/client-ses": "^3.888.0",
    "@aws-sdk/client-sns": "^3.887.0",
    "@aws-sdk/client-ssm": "^3.896.0",
    "@aws-sdk/lib-dynamodb": "^3.887.0",
    "@aws-sdk/lib-storage": "^3.896.0",
    "@axe-core/playwright": "^4.8.0",
    "@babel/preset-env": "^7.28.3",
    "@babel/preset-react": "^7.27.1",
    "@babel/preset-typescript": "^7.27.1",
    "@jest/globals": "29.7.0",
    "@lhci/cli": "^0.14.0",
    "@playwright/test": "^1.49.0",
    "@tanstack/react-query-devtools": "^5.87.4",
    "@testing-library/jest-dom": "^6.8.0",
    "@testing-library/react": "^16.3.0",
    "@testing-library/user-event": "^14.6.1",
    "@types/cors": "^2.8.17",
    "@types/express": "^4.17.21",
    "@types/jest": "29.5.12",
    "@types/node": "^20.19.17",
    "@types/pg": "^8.10.9",
    "@types/react": "^18.2.66",
    "@types/react-dom": "^18.2.22",
    "@types/supertest": "^6.0.2",
    "@typescript-eslint/eslint-plugin": "^7.2.0",
    "@typescript-eslint/parser": "^7.2.0",
    "@vitejs/plugin-react-swc": "^3.5.0",
    "artillery": "^2.0.0",
    "autoprefixer": "^10.4.19",
    "aws-cdk-lib": "^2.163.1",
    "aws-sdk-client-mock": "^4.1.0",
    "axe-core": "^4.8.0",
    "babel-jest": "^29.7.0",
    "concurrently": "^8.2.2",
    "constructs": "^10.0.0",
    "cors": "^2.8.5",
    "cross-env": "^7.0.3",
    "eslint": "^8.57.0",
    "eslint-plugin-react-hooks": "^4.6.0",
    "eslint-plugin-react-refresh": "^0.4.6",
    "express": "^4.21.2",
    "fast-glob": "^3.3.3",
    "husky": "^9.1.7",
    "jest": "29.7.0",
    "jest-environment-jsdom": "29.7.0",
    "jest-fetch-mock": "^3.0.3",
    "jest-junit": "^16.0.0",
    "jsdom": "^27.0.0",
    "madge": "^8.0.0",
    "pixelmatch": "^6.0.0",
    "pngjs": "^7.0.0",
    "postcss": "^8.4.38",
    "puppeteer-core": "^24.20.0",
    "rollup-plugin-visualizer": "^5.12.0",
    "supertest": "^6.3.4",
    "tailwindcss": "^3.4.1",
    "ts-jest": "^29.4.1",
    "typescript": "^5.2.2",
    "undici": "^7.16.0",
    "vite": "^5.2.0"
  },
  "overrides": {
    "@jest/*": "29.7.0",
    "jest-environment-jsdom": "29.7.0"
  }
}
